competitions_scheduler-0.2.5.post2-py2.7-nspkg.pth
competitions/scheduler/scheduler.py
competitions/scheduler/roundrobin.py
competitions/scheduler/__init__.py
competitions_scheduler-0.2.5.post2.dist-info/METADATA
competitions_scheduler-0.2.5.post2.dist-info/DESCRIPTION.rst
competitions_scheduler-0.2.5.post2.dist-info/RECORD
competitions_scheduler-0.2.5.post2.dist-info/WHEEL
competitions_scheduler-0.2.5.post2.dist-info/top_level.txt
competitions_scheduler-0.2.5.post2.dist-info/namespace_packages.txt
competitions_scheduler-0.2.5.post2.dist-info/metadata.json
