Metadata-Version: 2.0
Name: competitions-scheduler
Version: 0.2.5.post2
Summary: Generic schedulers for competitions
Home-page: https://github.com/happy5214/competitions-scheduler
Author: Alexander Jones
Author-email: happy5214@gmail.com
License: LGPLv3+
Keywords: competitions schedules roundrobin
Platform: UNKNOWN
Classifier: Development Status :: 3 - Alpha
Classifier: License :: OSI Approved :: GNU Lesser General Public License v3 or later (LGPLv3+)
Classifier: Programming Language :: Python :: 2.7
Classifier: Programming Language :: Python :: 3.2
Classifier: Programming Language :: Python :: 3.3
Classifier: Programming Language :: Python :: 3.4
